{"donations": 1000, "name": "Hillary Clinton (D)", "children": [{"donations": 50000, "name": "Individual", "children": [{"rate": 0.3333333333333333, "donations": 3, "name": "Abortion policy/Anti-Abortion", "value": 5100}, {"rate": 0.0045045045045045045, "donations": 222, "name": "Abortion policy/Pro-Abortion Rights", "value": 170455}, {"rate": 0.0006389776357827476, "donations": 1565, "name": "Accountants", "value": 1272468}, {"rate": 0.2, "donations": 5, "name": "Agricultural chemicals (fertilizers & pesticides)", "value": -300}, {"rate": 0.034482758620689655, "donations": 29, "name": "Agricultural services & related industries", "value": 25651}, {"rate": 0.03571428571428571, "donations": 28, "name": "Animal feed & health products", "value": 31224}, {"rate": 0.14285714285714285, "donations": 7, "name": "Farm bureaus", "value": 4550}, {"rate": 0.14285714285714285, "donations": 7, "name": "Farm machinery & equipment", "value": 5023}, {"rate": 0.2, "donations": 5, "name": "Farm organizations & cooperatives", "value": 3000}, {"rate": 0.014492753623188406, "donations": 69, "name": "Florists & Nursery Services", "value": 48110}, {"rate": 0.3333333333333333, "donations": 3, "name": "Grain traders & terminals", "value": 1300}, {"rate": 0.008771929824561403, "donations": 114, "name": "Veterinarians", "value": 64067}, {"rate": 0.2, "donations": 5, "name": "Air freight", "value": 750}, {"rate": 0.0303030303030303, "donations": 33, "name": "Air transport", "value": 29000}, {"rate": 0.14285714285714285, "donations": 7, "name": "Aircraft manufacturers", "value": 5600}, {"rate": 0.043478260869565216, "donations": 23, "name": "Aircraft parts & equipment", "value": 15200}, {"rate": 0.004651162790697675, "donations": 215, "name": "Airlines", "value": 114252}, {"rate": 0.04761904761904762, "donations": 21, "name": "Aviation services & airports", "value": 25700}, {"rate": 0.014705882352941175, "donations": 68, "name": "Express delivery services", "value": 43090}, {"rate": 0.04, "donations": 25, "name": "General aviation (private pilots)", "value": 12700}, {"rate": 0.038461538461538464, "donations": 26, "name": "Space vehicles & components", "value": 20100}, {"rate": 0.01694915254237288, "donations": 59, "name": "Auto dealers, foreign imports", "value": 34983}, {"rate": 0.006211180124223602, "donations": 161, "name": "Auto dealers, new & used", "value": 124009}, {"rate": 0.011111111111111112, "donations": 90, "name": "Auto manufacturers", "value": 41990}, {"rate": 0.021739130434782608, "donations": 46, "name": "Auto repair", "value": 33150}, {"rate": 0.037037037037037035, "donations": 27, "name": "Automotive, Misc", "value": 31684}, {"rate": 0.04347826086956522, "donations": 23, "name": "Car rental agencies", "value": 10800}, {"rate": 0.014492753623188406, "donations": 69, "name": "Truck/Automotive parts & accessories", "value": 62050}, {"rate": 1.0, "donations": 1, "name": "Alcohol", "value": 2300}, {"rate": 0.039999999999999994, "donations": 25, "name": "Beer", "value": 16520}, {"rate": 0.07692307692307693, "donations": 13, "name": "Liquor stores", "value": 13000}, {"rate": 0.011764705882352941, "donations": 85, "name": "Liquor wholesalers", "value": 79200}, {"rate": 0.006329113924050633, "donations": 158, "name": "Wine & distilled spirits manufacturing", "value": 154730}, {"rate": 0.0909090909090909, "donations": 11, "name": "Building materials", "value": 11350}, {"rate": 0.05882352941176471, "donations": 17, "name": "Construction equipment", "value": 15450}, {"rate": 0.14285714285714285, "donations": 7, "name": "Electrical Supply", "value": 7650}, {"rate": 0.02777777777777778, "donations": 36, "name": "Lumber and wood products", "value": 36077}, {"rate": 0.05263157894736842, "donations": 19, "name": "Other construction-related products", "value": 18650}, {"rate": 0.05263157894736842, "donations": 19, "name": "Plumbing & pipe products", "value": 14222}, {"rate": 0.0125, "donations": 80, "name": "Stone, clay, glass & concrete products", "value": 70650}, {"rate": 0.02, "donations": 50, "name": "Building trades unions", "value": 27425}, {"rate": 0.03333333333333333, "donations": 30, "name": "Chambers of commerce", "value": 22200}, {"rate": 0.0909090909090909, "donations": 11, "name": "General business associations", "value": 8300}, {"rate": 0.09090909090909091, "donations": 11, "name": "International trade associations", "value": 11600}, {"rate": 0.0011001100110011, "donations": 909, "name": "Advertising & public relations services", "value": 760791}, {"rate": 0.0003402517863218782, "donations": 2939, "name": "Business services", "value": 2105009}, {"rate": 0.0035587188612099642, "donations": 281, "name": "Commercial photography, art & graphic design", "value": 201030}, {"rate": 0.023809523809523808, "donations": 42, "name": "Direct mail advertising services", "value": 31185}, {"rate": 0.003003003003003003, "donations": 333, "name": "Employment agencies", "value": 220688}, {"rate": 0.0009940357852882705, "donations": 1006, "name": "Management consultants & services", "value": 872563}, {"rate": 0.004366812227074236, "donations": 229, "name": "Marketing research services", "value": 147950}, {"rate": 0.0588235294117647, "donations": 17, "name": "Outdoor advertising services", "value": 21150}, {"rate": 0.009900990099009901, "donations": 101, "name": "Political consultants/advisers", "value": 94385}, {"rate": 0.013513513513513514, "donations": 74, "name": "Security services", "value": 68163}, {"rate": 1.0, "donations": 1, "name": "Candidate contribution to his/her own campaign", "value": 1317500}, {"rate": 0.009433962264150943, "donations": 106, "name": "Casinos, racetracks & gambling", "value": 88816}, {"rate": 0.012658227848101267, "donations": 79, "name": "Indian Gaming", "value": 89375}, {"rate": 0.5, "donations": 2, "name": "Adhesives & Sealants", "value": 1000}, {"rate": 0.006493506493506493, "donations": 154, "name": "Chemicals", "value": 92084}, {"rate": 0.06666666666666667, "donations": 15, "name": "Household cleansers & chemicals", "value": 10458}, {"rate": 0.06666666666666667, "donations": 15, "name": "Paints, Solvents & Coatings", "value": 6850}, {"rate": 0.020408163265306124, "donations": 49, "name": "Plastics & Rubber processing & products", "value": 53794}, {"rate": 0.0002346316283435007, "donations": 4262, "name": "Civil servant/public employee", "value": 2104632}, {"rate": 0.0024509803921568627, "donations": 408, "name": "Courts & Justice System", "value": 240242}, {"rate": 0.006097560975609756, "donations": 164, "name": "Public official (elected or appointed)", "value": 113932}, {"rate": 0.008, "donations": 125, "name": "US Postal Service", "value": 44959}, {"rate": 0.00308641975308642, "donations": 324, "name": "Churches, clergy & religious organizations", "value": 215531}, {"rate": 0.0036496350364963502, "donations": 274, "name": "Banks & lending institutions", "value": 228808}, {"rate": 0.0006337135614702155, "donations": 1578, "name": "Commercial banks & bank holding companies", "value": 1262160}, {"rate": 0.0015151515151515152, "donations": 660, "name": "Architectural services", "value": 493579}, {"rate": 0.002617801047120419, "donations": 382, "name": "Engineering, architecture & construction mgmt svcs", "value": 337152}, {"rate": 0.002564102564102564, "donations": 390, "name": "Engineers - type unknown", "value": 255189}, {"rate": 0.03333333333333333, "donations": 30, "name": "Surveying", "value": 24225}, {"rate": 0.023255813953488372, "donations": 43, "name": "Credit unions", "value": 25970}, {"rate": 0.2, "donations": 5, "name": "Cotton", "value": 1825}, {"rate": 0.004608294930875576, "donations": 217, "name": "Crop production & basic processing", "value": 121221}, {"rate": 1.0, "donations": 1, "name": "Other commodities (incl rice, peanuts, honey)", "value": 250}, {"rate": 0.028571428571428574, "donations": 35, "name": "Sugar cane & sugar beets", "value": 46750}, {"rate": 0.03333333333333333, "donations": 30, "name": "Vegetables, fruits and tree nut", "value": 30520}, {"rate": 0.33333333333333337, "donations": 3, "name": "Wheat, corn, soybeans and cash grain", "value": 1250}, {"rate": 0.043478260869565216, "donations": 23, "name": "Milk & dairy producers", "value": 9700}, {"rate": 0.003968253968253968, "donations": 252, "name": "Defense aerospace contractors", "value": 130530}, {"rate": 0.0058479532163742695, "donations": 171, "name": "Defense electronic contractors", "value": 109863}, {"rate": 0.0009310986964618248, "donations": 1074, "name": "Democratic/Liberal", "value": 612236}, {"rate": 0.003067484662576687, "donations": 326, "name": "Education", "value": 180744}, {"rate": 0.006535947712418301, "donations": 153, "name": "For-profit Education", "value": 92790}, {"rate": 0.00546448087431694, "donations": 183, "name": "Law schools", "value": 106298}, {"rate": 0.002638522427440633, "donations": 379, "name": "Medical schools", "value": 226883}, {"rate": 0.0006333122229259025, "donations": 1579, "name": "Public school teachers, administrators & officials", "value": 726097}, {"rate": 0.000143143429716576, "donations": 6986, "name": "Schools & colleges", "value": 3498901}, {"rate": 0.016393442622950817, "donations": 61, "name": "Technical, business and vocational schools & svcs", "value": 40560}, {"rate": 0.01149425287356322, "donations": 87, "name": "Electric Power utilities", "value": 62313}, {"rate": 0.007462686567164179, "donations": 134, "name": "Gas & Electric Utilities", "value": 111987}, {"rate": 0.013698630136986302, "donations": 73, "name": "Independent power generation & cogeneration", "value": 115050}, {"rate": 0.14285714285714288, "donations": 7, "name": "Nuclear energy", "value": 5000}, {"rate": 0.09090909090909091, "donations": 11, "name": "Nuclear plant construction, equipment & svcs", "value": 10000}, {"rate": 0.5, "donations": 2, "name": "Rural electric cooperatives", "value": 1250}, {"rate": 0.0015015015015015015, "donations": 666, "name": "Computer components & accessories", "value": 470826}, {"rate": 0.002277904328018223, "donations": 439, "name": "Computer manufacture & services", "value": 232263}, {"rate": 0.0009372071227741331, "donations": 1067, "name": "Computer software", "value": 738879}, {"rate": 0.0015082956259426848, "donations": 663, "name": "Data processing & computer services", "value": 470435}, {"rate": 0.004694835680751174, "donations": 213, "name": "Electronics manufacturing & services", "value": 175175}, {"rate": 0.125, "donations": 8, "name": "Industrial Electronics", "value": 4250}, {"rate": 0.023809523809523808, "donations": 42, "name": "Telecommunications Devices", "value": 44400}, {"rate": 3.45411212047943e-05, "donations": 28951, "name": "Employer listed but category unknown", "value": 18709065}, {"rate": 0.004329004329004329, "donations": 231, "name": "Environmental policy", "value": 173019}, {"rate": 0.013888888888888888, "donations": 72, "name": "Environmental services, equipment & consulting", "value": 56051}, {"rate": 0.0038461538461538464, "donations": 260, "name": "Credit agencies & finance companies", "value": 220620}, {"rate": 0.125, "donations": 8, "name": "Payday lenders", "value": 5350}, {"rate": 0.07692307692307693, "donations": 13, "name": "Student loan companies", "value": 9550}, {"rate": 1.0, "donations": 1, "name": "Fisheries & wildlife", "value": 1300}, {"rate": 0.07142857142857144, "donations": 14, "name": "Beverage bottling & distribution", "value": 20100}, {"rate": 0.008771929824561403, "donations": 114, "name": "Beverages (non-alcoholic)", "value": 77133}, {"rate": 0.043478260869565216, "donations": 23, "name": "Confectionery processors & manufacturers", "value": 12800}, {"rate": 0.08333333333333333, "donations": 12, "name": "Fish Processing", "value": 8354}, {"rate": 0.011363636363636364, "donations": 88, "name": "Food catering & food services", "value": 79651}, {"rate": 0.0011614401858304297, "donations": 861, "name": "Restaurants & drinking establishments", "value": 718740}, {"rate": 0.029411764705882353, "donations": 34, "name": "Food & Beverage Products and Services", "value": 31500}, {"rate": 0.008849557522123894, "donations": 113, "name": "Food and kindred products manufacturing", "value": 72925}, {"rate": 0.0048543689320388345, "donations": 206, "name": "Food stores", "value": 148479}, {"rate": 0.021276595744680854, "donations": 47, "name": "Food wholesalers", "value": 51850}, {"rate": 0.030303030303030304, "donations": 33, "name": "Meat processing & products", "value": 22650}, {"rate": 0.041666666666666664, "donations": 24, "name": "Anti-Castro", "value": 20950}, {"rate": 0.09090909090909091, "donations": 11, "name": "Defense policy, doves", "value": 12100}, {"rate": 0.1, "donations": 10, "name": "Defense policy, hawks", "value": 1950}, {"rate": 0.0125, "donations": 80, "name": "Foreign policy", "value": 83950}, {"rate": 0.25, "donations": 4, "name": "Pro-Arab", "value": 7400}, {"rate": 1.0, "donations": 1, "name": "Puerto Rico statehood policy", "value": 500}, {"rate": 0.03225806451612903, "donations": 31, "name": "Forestry & Forest Products", "value": 10762}, {"rate": 0.02564102564102564, "donations": 39, "name": "Paper & pulp mills and paper manufacturing", "value": 42350}, {"rate": 0.1111111111111111, "donations": 9, "name": "Builders associations", "value": 1850}, {"rate": 0.05555555555555555, "donations": 18, "name": "Construction & Public Works", "value": 18900}, {"rate": 0.00129366106080207, "donations": 773, "name": "Construction, unclassified", "value": 663299}, {"rate": 0.0038314176245210726, "donations": 261, "name": "Public works, industrial & commercial construction", "value": 260600}, {"rate": 0.022222222222222223, "donations": 45, "name": "Generic occupation - impossible to assign category", "value": 28625}, {"rate": 1.0, "donations": 1, "name": "Anti-Guns", "value": 2300}, {"rate": 0.07142857142857142, "donations": 14, "name": "Pro-Guns", "value": 7000}, {"rate": 0.023255813953488372, "donations": 43, "name": "Chiropractors", "value": 20625}, {"rate": 0.0019417475728155341, "donations": 515, "name": "Dentists", "value": 322379}, {"rate": 0.04, "donations": 25, "name": "Health professionals", "value": 20000}, {"rate": 0.004830917874396136, "donations": 207, "name": "Nurses", "value": 126935}, {"rate": 0.011627906976744186, "donations": 86, "name": "Optometrists & Ophthalmologists", "value": 57185}, {"rate": 0.0035971223021582736, "donations": 278, "name": "Other non-physician health practitioners", "value": 184979}, {"rate": 0.0009115770282588879, "donations": 1097, "name": "Other physician specialists", "value": 799813}, {"rate": 0.0196078431372549, "donations": 51, "name": "Pharmacists", "value": 38170}, {"rate": 0.0003278688524590164, "donations": 3050, "name": "Physicians", "value": 2098791}, {"rate": 0.0011123470522803114, "donations": 899, "name": "Psychiatrists & psychologists", "value": 482425}, {"rate": 0.03703703703703704, "donations": 27, "name": "AIDS treatment & testing", "value": 14350}, {"rate": 0.00423728813559322, "donations": 236, "name": "HMOs", "value": 177245}, {"rate": 0.011627906976744186, "donations": 86, "name": "Health care Consultants", "value": 60889}, {"rate": 0.005154639175257732, "donations": 194, "name": "Health care services", "value": 162674}, {"rate": 0.007575757575757576, "donations": 132, "name": "Home care services", "value": 118500}, {"rate": 0.020833333333333332, "donations": 48, "name": "Medical laboratories", "value": 41550}, {"rate": 0.0136986301369863, "donations": 73, "name": "Mental Health Services", "value": 64962}, {"rate": 0.5, "donations": 2, "name": "Optical services (glasses & contact lenses)", "value": 2000}, {"rate": 0.02380952380952381, "donations": 42, "name": "Outpatient health services (incl drug & alcohol)", "value": 31200}, {"rate": 0.16666666666666666, "donations": 6, "name": "Mobile home construction", "value": 6350}, {"rate": 0.0038610038610038607, "donations": 259, "name": "Residential construction", "value": 217429}, {"rate": 9.363295880149812e-05, "donations": 10680, "name": "Homemakers, students & other non-income earners", "value": 6683933}, {"rate": 0.11111111111111112, "donations": 9, "name": "Drug & alcohol treatment hospitals", "value": 12500}, {"rate": 0.0035211267605633804, "donations": 284, "name": "Health care institutions", "value": 130016}, {"rate": 0.0006116207951070337, "donations": 1635, "name": "Hospitals", "value": 829032}, {"rate": 0.00641025641025641, "donations": 156, "name": "Nursing homes", "value": 143476}, {"rate": 0.025, "donations": 40, "name": "Children's rights", "value": 38450}, {"rate": 0.012820512820512822, "donations": 78, "name": "Gay & lesbian rights & issues", "value": 60732}, {"rate": 0.010309278350515464, "donations": 97, "name": "Health & welfare policy", "value": 64250}, {"rate": 0.045454545454545456, "donations": 22, "name": "Human Rights", "value": 15900}, {"rate": 0.002544529262086514, "donations": 393, "name": "Minority/Ethnic Groups", "value": 377604}, {"rate": 0.2, "donations": 5, "name": "Native American Tribes", "value": 10450}, {"rate": 0.125, "donations": 8, "name": "Automotive Manufacturing union", "value": 6350}, {"rate": 0.1111111111111111, "donations": 9, "name": "Communications & hi-tech unions", "value": 4300}, {"rate": 0.2, "donations": 5, "name": "IBEW (Intl Brotherhood of Electrical Workers)", "value": 6050}, {"rate": 0.125, "donations": 8, "name": "Manufacturing unions", "value": 3500}, {"rate": 0.00546448087431694, "donations": 183, "name": "Accident & health insurance", "value": 126625}, {"rate": 0.011235955056179775, "donations": 89, "name": "Insurance", "value": 79620}, {"rate": 0.0010706638115631692, "donations": 934, "name": "Insurance companies, brokers & agents", "value": 681266}, {"rate": 0.003278688524590164, "donations": 305, "name": "Life insurance", "value": 283488}, {"rate": 0.007142857142857143, "donations": 140, "name": "Property & casualty insurance", "value": 69251}, {"rate": 0.004032258064516129, "donations": 248, "name": "Internet & Online Services", "value": 131962}, {"rate": 0.058823529411764705, "donations": 17, "name": "Online Entertainment", "value": 22450}, {"rate": 0.00641025641025641, "donations": 156, "name": "Search Engine/Email Services", "value": 116325}, {"rate": 0.0625, "donations": 16, "name": "Social Media", "value": 18925}, {"rate": 0.010416666666666666, "donations": 96, "name": "Vendors", "value": 78750}, {"rate": 5.829544129649062e-05, "donations": 17154, "name": "Attorneys & law firms", "value": 14067242}, {"rate": 0.0005691519635742742, "donations": 1757, "name": "Corporate lawyers & law firms", "value": 1659995}, {"rate": 0.020833333333333332, "donations": 48, "name": "Legal Services", "value": 44450}, {"rate": 0.0021008403361344537, "donations": 476, "name": "Trial lawyers & law firms", "value": 537044}, {"rate": 0.2, "donations": 5, "name": "Democratic leadership PAC", "value": 2750}, {"rate": 0.2, "donations": 5, "name": "Democratic officials, candidates & former members", "value": 2700}, {"rate": 0.3333333333333333, "donations": 3, "name": "Non-Federal candidate committees", "value": 5100}, {"rate": 0.3333333333333333, "donations": 3, "name": "Republican leadership PAC", "value": 2013}, {"rate": 0.041666666666666664, "donations": 24, "name": "Horse breeders", "value": 16900}, {"rate": 0.008620689655172414, "donations": 116, "name": "Livestock", "value": 100739}, {"rate": 0.33333333333333337, "donations": 3, "name": "Sheep and Wool Producers", "value": 1250}, {"rate": 0.0006770480704129993, "donations": 1477, "name": "Lobbyists & Public Relations", "value": 1513696}, {"rate": 0.0023584905660377358, "donations": 424, "name": "Hotels & motels", "value": 359312}, {"rate": 0.05, "donations": 20, "name": "Lodging & tourism", "value": 15350}, {"rate": 0.028571428571428574, "donations": 35, "name": "Resorts", "value": 39400}, {"rate": 0.011235955056179775, "donations": 89, "name": "Travel agents", "value": 59258}, {"rate": 0.047619047619047616, "donations": 21, "name": "Coal mining", "value": 20600}, {"rate": 0.16666666666666666, "donations": 6, "name": "Metal mining & processing", "value": 4450}, {"rate": 0.06666666666666667, "donations": 15, "name": "Mining", "value": 7350}, {"rate": 0.5, "donations": 2, "name": "Mining services & equipment", "value": 3300}, {"rate": 0.3333333333333333, "donations": 3, "name": "Non-metallic mining", "value": 6900}, {"rate": 0.027777777777777776, "donations": 36, "name": "Agriculture", "value": 16500}, {"rate": 0.25, "donations": 4, "name": "Correctional facilities constr & mgmt/for-profit", "value": 3800}, {"rate": 0.0002781641168289291, "donations": 3595, "name": "General commerce", "value": 3156099}, {"rate": 0.024390243902439025, "donations": 41, "name": "Import/Export services", "value": 32239}, {"rate": 0.08333333333333333, "donations": 12, "name": "Warehousing", "value": 5700}, {"rate": 0.04166666666666667, "donations": 24, "name": "Wholesale trade", "value": 14000}, {"rate": 0.02127659574468085, "donations": 47, "name": "Communications & Electronics", "value": 47490}, {"rate": 0.125, "donations": 8, "name": "Defense", "value": 4550}, {"rate": 0.05, "donations": 20, "name": "Defense Research & Development", "value": 11250}, {"rate": 0.012048192771084338, "donations": 83, "name": "Defense shipbuilders", "value": 51438}, {"rate": 0.01234567901234568, "donations": 81, "name": "Defense-related services", "value": 63020}, {"rate": 0.08333333333333334, "donations": 12, "name": "Ground-based & other weapons systems", "value": 8872}, {"rate": 0.03125, "donations": 32, "name": "Homeland Security contractors", "value": 33750}, {"rate": 0.029411764705882353, "donations": 34, "name": "Alternate energy production & services", "value": 42075}, {"rate": 0.0055248618784530384, "donations": 181, "name": "Energy production & distribution", "value": 148789}, {"rate": 0.3333333333333333, "donations": 3, "name": "Energy, Natural Resources and Environment", "value": 2750}, {"rate": 0.05555555555555555, "donations": 18, "name": "Power plant construction & equipment", "value": 10100}, {"rate": 0.058823529411764705, "donations": 17, "name": "Water Utilities", "value": 13550}, {"rate": 0.013513513513513513, "donations": 74, "name": "Credit reporting services & collection agencies", "value": 47203}, {"rate": 0.0008936550491510278, "donations": 1119, "name": "Finance, Insurance & Real Estate", "value": 968999}, {"rate": 0.0036101083032490976, "donations": 277, "name": "Financial services & consulting", "value": 226975}, {"rate": 0.00089126559714795, "donations": 1122, "name": "Investors", "value": 1172902}, {"rate": 0.005235602094240837, "donations": 191, "name": "Other financial services", "value": 139775}, {"rate": 0.015384615384615385, "donations": 65, "name": "Tax return services", "value": 33119}, {"rate": 0.001858736059479554, "donations": 538, "name": "Health, Education & Human Resources", "value": 302734}, {"rate": 0.04, "donations": 25, "name": "Animal Rights", "value": 24475}, {"rate": 0.0625, "donations": 16, "name": "Elderly issues/Social Security", "value": 6350}, {"rate": 1.0, "donations": 1, "name": "Fiscal & tax policy", "value": 500}, {"rate": 0.010989010989010988, "donations": 91, "name": "Other single-issue or ideological groups", "value": 86173}, {"rate": 0.052631578947368425, "donations": 19, "name": "Aluminum mining/processing", "value": 24501}, {"rate": 0.16666666666666666, "donations": 6, "name": "Clocks & watches", "value": 4600}, {"rate": 0.00303951367781155, "donations": 329, "name": "Clothing & accessories", "value": 296233}, {"rate": 0.07142857142857142, "donations": 14, "name": "Electrical lighting products", "value": 14650}, {"rate": 1.0, "donations": 1, "name": "Electroplating, polishing & related services", "value": 2000}, {"rate": 0.015625, "donations": 64, "name": "Fabricated metal products", "value": 66500}, {"rate": 0.023255813953488372, "donations": 43, "name": "Furniture & wood products", "value": 38650}, {"rate": 0.02857142857142857, "donations": 35, "name": "Glass products", "value": 30020}, {"rate": 0.06666666666666667, "donations": 15, "name": "Hardware & tools", "value": 10150}, {"rate": 0.125, "donations": 8, "name": "Heavy industrial manufacturing", "value": 14750}, {"rate": 0.034482758620689655, "donations": 29, "name": "Household & office products", "value": 25468}, {"rate": 0.25, "donations": 4, "name": "Household appliances", "value": 1650}, {"rate": 0.004132231404958678, "donations": 242, "name": "Industrial/commercial equipment & materials", "value": 198161}, {"rate": 0.0136986301369863, "donations": 73, "name": "Jewelry", "value": 62450}, {"rate": 0.14285714285714285, "donations": 7, "name": "Manmade fibers", "value": 6900}, {"rate": 0.020833333333333336, "donations": 48, "name": "Manufacturing", "value": 40300}, {"rate": 0.09090909090909091, "donations": 11, "name": "Metal cans & containers", "value": 12900}, {"rate": 0.021739130434782608, "donations": 46, "name": "Office machines", "value": 25800}, {"rate": 0.058823529411764705, "donations": 17, "name": "Optical instruments & lenses", "value": 21600}, {"rate": 0.037037037037037035, "donations": 27, "name": "Paper packaging materials", "value": 39050}, {"rate": 0.026315789473684213, "donations": 38, "name": "Paper, glass & packaging materials", "value": 21600}, {"rate": 0.06666666666666667, "donations": 15, "name": "Personal products manufacturing", "value": 14800}, {"rate": 0.04, "donations": 25, "name": "Photographic equipment & supplies", "value": 19250}, {"rate": 0.02040816326530612, "donations": 49, "name": "Precision instruments", "value": 48250}, {"rate": 0.04, "donations": 25, "name": "Recycling of metal, paper, plastics, etc.", "value": 24600}, {"rate": 0.02777777777777778, "donations": 36, "name": "Shoes & leather products", "value": 20302}, {"rate": 0.09090909090909091, "donations": 11, "name": "Small arms & ammunition", "value": 8100}, {"rate": 0.05263157894736842, "donations": 19, "name": "Smelting & non-petroleum refining", "value": 26850}, {"rate": 0.05882352941176471, "donations": 17, "name": "Sporting goods sales & manufacturing", "value": 15450}, {"rate": 0.006134969325153374, "donations": 163, "name": "Toiletries & cosmetics", "value": 137116}, {"rate": 0.03125, "donations": 32, "name": "Toys", "value": 23300}, {"rate": 0.007751937984496124, "donations": 129, "name": "Beauty & barber shops", "value": 65890}, {"rate": 0.019230769230769232, "donations": 52, "name": "Equipment rental & leasing", "value": 40707}, {"rate": 0.023255813953488375, "donations": 43, "name": "Funeral services", "value": 33014}, {"rate": 0.024390243902439025, "donations": 41, "name": "Laundries & dry cleaners", "value": 36650}, {"rate": 0.1111111111111111, "donations": 9, "name": "Miscellaneous repair services", "value": 6454}, {"rate": 0.25, "donations": 4, "name": "Pest control", "value": 2150}, {"rate": 0.012658227848101267, "donations": 79, "name": "Physical fitness centers", "value": 41088}, {"rate": 0.0012468827930174563, "donations": 802, "name": "Services", "value": 616487}, {"rate": 0.25, "donations": 4, "name": "Video rental", "value": 2550}, {"rate": 1.0, "donations": 1, "name": "Bicycles & other non-motorized recreational transp", "value": 500}, {"rate": 0.07142857142857144, "donations": 14, "name": "Bus services", "value": 12100}, {"rate": 0.09090909090909091, "donations": 11, "name": "Buses & Taxis", "value": 10283}, {"rate": 0.06666666666666667, "donations": 15, "name": "Freight & delivery services", "value": 15950}, {"rate": 0.3333333333333333, "donations": 3, "name": "Motor homes & camper trailers", "value": 4900}, {"rate": 0.2, "donations": 5, "name": "Motorcycles, snowmobiles & other motorized vehicle", "value": 5600}, {"rate": 0.08333333333333333, "donations": 12, "name": "Pleasure boats", "value": 9350}, {"rate": 0.030303030303030304, "donations": 33, "name": "Taxicabs", "value": 21203}, {"rate": 0.023809523809523808, "donations": 42, "name": "Transportation", "value": 32550}, {"rate": 1.0, "donations": 1, "name": "Agricultural labor unions", "value": 250}, {"rate": 0.05, "donations": 20, "name": "Commercial service unions", "value": 10080}, {"rate": 0.04347826086956522, "donations": 23, "name": "Entertainment unions", "value": 18150}, {"rate": 0.5, "donations": 2, "name": "Food service & related unions", "value": 1250}, {"rate": 0.5, "donations": 2, "name": "General commercial unions", "value": 1200}, {"rate": 0.047619047619047616, "donations": 21, "name": "Labor Unions", "value": 12738}, {"rate": 0.00010513036164844408, "donations": 9512, "name": "No employer listed or discovered", "value": 2928085}, {"rate": 0.002506265664160401, "donations": 399, "name": "Museums, art galleries, libraries, etc.", "value": 266040}, {"rate": 0.0028901734104046246, "donations": 346, "name": "Non-Profits", "value": 272223}, {"rate": 0.0024449877750611247, "donations": 409, "name": "Non-profit foundations", "value": 394577}, {"rate": 0.009615384615384616, "donations": 104, "name": "Philanthropists", "value": 117568}, {"rate": 1.0, "donations": 1, "name": "Non-Contribution, Miscellaneous", "value": 1500}, {"rate": 0.0010245901639344263, "donations": 976, "name": "Transfer from intermediary ( type 24I or 24T)", "value": 453784}, {"rate": 1.0, "donations": 1, "name": "Unitemized (small) contributions", "value": 555773}, {"rate": 0.125, "donations": 8, "name": "Fuel oil dealers", "value": 6590}, {"rate": 0.02631578947368421, "donations": 38, "name": "Gasoline service stations", "value": 33050}, {"rate": 0.023255813953488372, "donations": 43, "name": "Independent oil & gas producers", "value": 34700}, {"rate": 1.0, "donations": 1, "name": "LPG/Liquid Propane dealers & producers", "value": 2300}, {"rate": 0.00617283950617284, "donations": 162, "name": "Major (multinational) oil & gas producers", "value": 98320}, {"rate": 0.02040816326530612, "donations": 49, "name": "Natural Gas transmission & distribution", "value": 42807}, {"rate": 0.0125, "donations": 80, "name": "Oil & Gas", "value": 68550}, {"rate": 0.012987012987012986, "donations": 77, "name": "Oilfield service, equipment & exploration", "value": 64350}, {"rate": 0.020833333333333332, "donations": 48, "name": "Petroleum refining & marketing", "value": 43775}, {"rate": 0.5, "donations": 2, "name": "Foreign Governments", "value": 500}, {"rate": 0.01075268817204301, "donations": 93, "name": "International Organizations", "value": 49769}, {"rate": 0.002331002331002331, "donations": 429, "name": "Military", "value": 174294}, {"rate": 0.0012836970474967909, "donations": 779, "name": "Other", "value": 522471}, {"rate": 0.003846153846153846, "donations": 260, "name": "Welfare & Social Work", "value": 141560}, {"rate": 0.00546448087431694, "donations": 183, "name": "Biotech products & research", "value": 133697}, {"rate": 0.009433962264150943, "donations": 106, "name": "Health care products", "value": 62150}, {"rate": 0.005076142131979695, "donations": 197, "name": "Medical Devices & Supplies", "value": 126309}, {"rate": 0.07692307692307691, "donations": 13, "name": "Nutritional & dietary supplements", "value": 16400}, {"rate": 0.09090909090909091, "donations": 11, "name": "Personal health care products", "value": 13323}, {"rate": 1.0, "donations": 1, "name": "Pharmaceutical cannabis", "value": 250}, {"rate": 0.0016233766233766235, "donations": 616, "name": "Pharmaceutical manufacturing", "value": 340534}, {"rate": 0.021739130434782608, "donations": 46, "name": "Pharmaceutical wholesale", "value": 22496}, {"rate": 0.1, "donations": 10, "name": "Poultry & eggs", "value": 14200}, {"rate": 0.00046728971962616824, "donations": 2140, "name": "Book, newspaper & periodical publishing", "value": 1438684}, {"rate": 0.004484304932735426, "donations": 223, "name": "Commercial printing & typesetting", "value": 119438}, {"rate": 0.07142857142857144, "donations": 14, "name": "Greeting card publishing", "value": 15004}, {"rate": 0.047619047619047616, "donations": 21, "name": "Printing and publishing (printed & online)", "value": 22050}, {"rate": 0.0017513134851138354, "donations": 571, "name": "Pro-Israel", "value": 620875}, {"rate": 0.5, "donations": 2, "name": "Federal employees unions", "value": 1550}, {"rate": 0.2, "donations": 5, "name": "Police & firefighters unions & associations", "value": 2064}, {"rate": 0.010638297872340425, "donations": 94, "name": "State & local govt employee unions", "value": 41359}, {"rate": 0.0072992700729927005, "donations": 137, "name": "Teachers unions", "value": 66010}, {"rate": 0.16666666666666666, "donations": 6, "name": "US Postal Service unions & associations", "value": 2700}, {"rate": 0.3333333333333333, "donations": 3, "name": "Manufacturers of railroad equipment", "value": 6900}, {"rate": 0.5, "donations": 2, "name": "Railroad services", "value": 450}, {"rate": 1.0, "donations": 1, "name": "Railroad transportation", "value": 200}, {"rate": 0.017543859649122806, "donations": 57, "name": "Railroads", "value": 37287}, {"rate": 0.0017605633802816902, "donations": 568, "name": "Building operators and managers", "value": 490956}, {"rate": 0.08333333333333334, "donations": 12, "name": "Mobile home dealers & parks", "value": 5150}, {"rate": 0.0022988505747126436, "donations": 435, "name": "Mortgage bankers and brokers", "value": 253423}, {"rate": 0.0136986301369863, "donations": 73, "name": "Other real estate services", "value": 50450}, {"rate": 0.00065359477124183, "donations": 1530, "name": "Real Estate developers & subdividers", "value": 1798292}, {"rate": 0.0003898635477582846, "donations": 2565, "name": "Real estate", "value": 2162382}, {"rate": 0.00041339396444811904, "donations": 2419, "name": "Real estate agents", "value": 1815734}, {"rate": 0.006172839506172839, "donations": 162, "name": "Title insurance & title abstract offices", "value": 139550}, {"rate": 0.02857142857142857, "donations": 35, "name": "Amusement parks", "value": 30800}, {"rate": 0.015873015873015872, "donations": 63, "name": "Amusement/recreation centers", "value": 48950}, {"rate": 0.005681818181818181, "donations": 176, "name": "Professional sports, arenas & related equip & svcs", "value": 189700}, {"rate": 0.022222222222222223, "donations": 45, "name": "Recreation/Entertainment", "value": 55150}, {"rate": 0.008695652173913044, "donations": 115, "name": "Republican/Conservative", "value": 40192}, {"rate": 0.003472222222222222, "donations": 288, "name": "Apparel & accessory stores", "value": 231080}, {"rate": 0.25, "donations": 4, "name": "Catalog & mail order houses", "value": 7600}, {"rate": 0.013513513513513513, "donations": 74, "name": "Consumer electronics & computer stores", "value": 62415}, {"rate": 0.005376344086021506, "donations": 186, "name": "Department, variety & convenience stores", "value": 131284}, {"rate": 0.04, "donations": 25, "name": "Direct sales", "value": 19000}, {"rate": 0.005649717514124295, "donations": 177, "name": "Drug stores", "value": 123938}, {"rate": 0.02702702702702703, "donations": 37, "name": "Furniture & appliance stores", "value": 35950}, {"rate": 0.027027027027027025, "donations": 37, "name": "Hardware & building materials stores", "value": 29450}, {"rate": 0.0023094688221709007, "donations": 433, "name": "Miscellaneous retail stores", "value": 322783}, {"rate": 0.006944444444444444, "donations": 144, "name": "Retail trade", "value": 104558}, {"rate": 4.5405012713403555e-05, "donations": 22024, "name": "Retired", "value": 11429687}, {"rate": 0.015625, "donations": 64, "name": "Savings banks & Savings and Loans", "value": 40705}, {"rate": 0.05263157894736842, "donations": 19, "name": "Cruise ships & lines", "value": 26400}, {"rate": 0.023809523809523808, "donations": 42, "name": "Sea freight & passenger services", "value": 38750}, {"rate": 0.14285714285714288, "donations": 7, "name": "Sea transport", "value": 3800}, {"rate": 0.04, "donations": 25, "name": "Ship building & repair", "value": 15950}, {"rate": 0.013698630136986302, "donations": 73, "name": "Commodity brokers/dealers", "value": 114700}, {"rate": 0.005917159763313609, "donations": 169, "name": "Discount & Online Brokers", "value": 54796}, {"rate": 0.0013812154696132598, "donations": 724, "name": "Hedge Funds", "value": 828389}, {"rate": 0.0007457121551081282, "donations": 1341, "name": "Investment banking", "value": 1456559}, {"rate": 0.0012547051442910917, "donations": 797, "name": "Private Equity & Investment Firms", "value": 993813}, {"rate": 0.004424778761061947, "donations": 226, "name": "Securities, commodities & investment", "value": 209710}, {"rate": 0.0003095975232198142, "donations": 3230, "name": "Security brokers & investment companies", "value": 3257227}, {"rate": 0.02, "donations": 50, "name": "Stock exchanges", "value": 76650}, {"rate": 0.002583979328165375, "donations": 387, "name": "Venture capital", "value": 444600}, {"rate": 0.007194244604316546, "donations": 139, "name": "Electrical contractors", "value": 121105}, {"rate": 0.007352941176470588, "donations": 136, "name": "Landscaping & Excavation Svcs", "value": 99228}, {"rate": 0.01, "donations": 100, "name": "Plumbing, heating & air conditioning", "value": 94950}, {"rate": 0.004807692307692307, "donations": 208, "name": "Special trade contractors", "value": 150505}, {"rate": 0.023809523809523808, "donations": 42, "name": "Steel", "value": 39250}, {"rate": 0.014285714285714285, "donations": 70, "name": "Bands, orchestras & other live music production", "value": 55615}, {"rate": 0.003968253968253968, "donations": 252, "name": "Cable & satellite TV production", "value": 222954}, {"rate": 0.002538071065989848, "donations": 394, "name": "Commercial TV & radio stations", "value": 324779}, {"rate": 0.0015174506828528073, "donations": 659, "name": "Entertainment Industry/Broadcast & Motion Pictures", "value": 514530}, {"rate": 0.0049261083743842365, "donations": 203, "name": "Live theater & other entertainment productions", "value": 154418}, {"rate": 0.0008045052292839904, "donations": 1243, "name": "Motion Picture production & distribution", "value": 1131791}, {"rate": 0.05555555555555555, "donations": 18, "name": "Movie Theaters", "value": 17400}, {"rate": 0.002967359050445104, "donations": 337, "name": "Recorded Music & music production", "value": 282584}, {"rate": 0.002403846153846154, "donations": 416, "name": "TV production", "value": 415376}, {"rate": 0.0038314176245210726, "donations": 261, "name": "Cable distributors & service providers", "value": 264465}, {"rate": 0.008695652173913044, "donations": 115, "name": "Cell/wireless service providers", "value": 86080}, {"rate": 0.007751937984496125, "donations": 129, "name": "Other Communications Services", "value": 110850}, {"rate": 0.0070921985815602835, "donations": 141, "name": "Satellite communications", "value": 186200}, {"rate": 0.012195121951219513, "donations": 82, "name": "Telecommunications", "value": 80295}, {"rate": 0.025, "donations": 40, "name": "Long-distance telephone & telegraph service", "value": 29425}, {"rate": 0.002840909090909091, "donations": 352, "name": "Telephone utilities", "value": 215652}, {"rate": 0.011904761904761904, "donations": 84, "name": "Textiles & fabrics", "value": 82120}, {"rate": 0.024390243902439025, "donations": 41, "name": "Tobacco & Tobacco products", "value": 55000}, {"rate": 0.05882352941176471, "donations": 17, "name": "Merchant marine & longshoremen unions", "value": 6772}, {"rate": 1.0, "donations": 1, "name": "Other transportation unions", "value": 250}, {"rate": 0.33333333333333337, "donations": 3, "name": "Teamsters union", "value": 950}, {"rate": 0.25, "donations": 4, "name": "Transportation unions", "value": 5100}, {"rate": 0.5, "donations": 2, "name": "Truck & trailer manufacturers", "value": 2550}, {"rate": 0.25, "donations": 4, "name": "Trucking", "value": 2500}, {"rate": 0.009174311926605503, "donations": 109, "name": "Trucking companies & services", "value": 76446}, {"rate": 1.0, "donations": 1, "name": "Unknown", "value": 250}, {"rate": 0.014705882352941176, "donations": 68, "name": "Waste management", "value": 53775}, {"rate": 0.00012309207287050715, "donations": 8124, "name": "Women's issues", "value": 5624267}]}, {"donations": 1000, "name": "PACs", "children": [{"rate": 0.027027027027027025, "donations": 37, "name": "Abortion policy/Anti-Abortion", "value": 779352}, {"rate": 0.028571428571428574, "donations": 35, "name": "Abortion policy/Pro-Abortion Rights", "value": 26292}, {"rate": 0.25, "donations": 4, "name": "Accountants", "value": 15000}, {"rate": 1.0, "donations": 1, "name": "Veterinarians", "value": 2000}, {"rate": 0.5, "donations": 2, "name": "Airlines", "value": 7300}, {"rate": 1.0, "donations": 1, "name": "Express delivery services", "value": 5000}, {"rate": 1.0, "donations": 1, "name": "Car rental agencies", "value": 5000}, {"rate": 1.0, "donations": 1, "name": "Truck/Automotive parts & accessories", "value": 1000}, {"rate": 0.33333333333333337, "donations": 3, "name": "Alcohol", "value": 5000}, {"rate": 1.0, "donations": 1, "name": "Liquor wholesalers", "value": 5000}, {"rate": 0.0, "donations": 2, "name": "Wine & distilled spirits manufacturing", "value": 0}, {"rate": 1.0, "donations": 1, "name": "Building materials", "value": 500}, {"rate": 1.0, "donations": 1, "name": "Other construction-related products", "value": 5000}, {"rate": 0.5, "donations": 2, "name": "Stone, clay, glass & concrete products", "value": 6000}, {"rate": 0.017543859649122806, "donations": 57, "name": "Building trades unions", "value": 199233}, {"rate": 0.009433962264150943, "donations": 106, "name": "Democratic Candidate Committees", "value": 173223}, {"rate": 1.0, "donations": 1, "name": "Third-Party Candidate Committees", "value": 500}, {"rate": 1.0, "donations": 1, "name": "Casinos, racetracks & gambling", "value": 2500}, {"rate": 0.3333333333333333, "donations": 3, "name": "Chemicals", "value": 12300}, {"rate": 0.08333333333333333, "donations": 12, "name": "Commercial banks & bank holding companies", "value": 26150}, {"rate": 0.1, "donations": 10, "name": "Engineering, architecture & construction mgmt svcs", "value": 20900}, {"rate": 1.0, "donations": 1, "name": "Credit unions", "value": 2300}, {"rate": 0.25, "donations": 4, "name": "Sugar cane & sugar beets", "value": 6800}, {"rate": 1.0, "donations": 1, "name": "Milk & dairy producers", "value": 500}, {"rate": 0.14285714285714285, "donations": 7, "name": "Defense electronic contractors", "value": 11800}, {"rate": 0.012195121951219513, "donations": 82, "name": "Democratic/Liberal", "value": 166336}, {"rate": 1.0, "donations": 1, "name": "Education", "value": 1000}, {"rate": 0.16666666666666666, "donations": 6, "name": "Gas & Electric Utilities", "value": 10500}, {"rate": 0.5, "donations": 2, "name": "Independent power generation & cogeneration", "value": 10000}, {"rate": 1.0, "donations": 1, "name": "Computer components & accessories", "value": 1000}, {"rate": 1.0, "donations": 1, "name": "Computer manufacture & services", "value": 70}, {"rate": 1.0, "donations": 1, "name": "Electronics manufacturing & services", "value": 5000}, {"rate": 1.0, "donations": 1, "name": "Telecommunications Devices", "value": 5000}, {"rate": 0.5, "donations": 2, "name": "Environmental services, equipment & consulting", "value": 10000}, {"rate": 1.0, "donations": 1, "name": "Beverage bottling & distribution", "value": 5000}, {"rate": 0.33333333333333337, "donations": 3, "name": "Beverages (non-alcoholic)", "value": 5000}, {"rate": 0.25, "donations": 4, "name": "Food catering & food services", "value": 6850}, {"rate": 1.0, "donations": 1, "name": "Food and kindred products manufacturing", "value": 2000}, {"rate": 1.0, "donations": 1, "name": "Food stores", "value": 2300}, {"rate": 1.0, "donations": 1, "name": "Construction & Public Works", "value": 1000}, {"rate": 0.5, "donations": 2, "name": "Public works, industrial & commercial construction", "value": 6000}, {"rate": 0.5, "donations": 2, "name": "Dentists", "value": 6000}, {"rate": 0.05555555555555556, "donations": 18, "name": "Nurses", "value": 18042}, {"rate": 1.0, "donations": 1, "name": "Other physician specialists", "value": 5000}, {"rate": 1.0, "donations": 1, "name": "Physicians", "value": 1000}, {"rate": 0.2, "donations": 5, "name": "HMOs", "value": 4050}, {"rate": 1.0, "donations": 1, "name": "Home care services", "value": 1000}, {"rate": 0.3333333333333333, "donations": 3, "name": "Outpatient health services (incl drug & alcohol)", "value": 15000}, {"rate": 0.125, "donations": 8, "name": "Hospitals", "value": 14500}, {"rate": 1.0, "donations": 1, "name": "Nursing homes", "value": 1500}, {"rate": 0.041666666666666664, "donations": 24, "name": "Minority/Ethnic Groups", "value": 45029}, {"rate": 1.0, "donations": 1, "name": "Automotive Manufacturing union", "value": 5000}, {"rate": 1.0, "donations": 1, "name": "Communications & hi-tech unions", "value": 5000}, {"rate": 0.25, "donations": 4, "name": "IBEW (Intl Brotherhood of Electrical Workers)", "value": 16000}, {"rate": 0.017241379310344827, "donations": 58, "name": "Manufacturing unions", "value": 272706}, {"rate": 1.0, "donations": 1, "name": "Mining unions", "value": 2500}, {"rate": 0.2, "donations": 5, "name": "Accident & health insurance", "value": 9850}, {"rate": 0.3333333333333333, "donations": 3, "name": "Life insurance", "value": 12300}, {"rate": 1.0, "donations": 1, "name": "Internet & Online Services", "value": 2500}, {"rate": 0.01694915254237288, "donations": 59, "name": "Attorneys & law firms", "value": 141400}, {"rate": 0.09090909090909091, "donations": 11, "name": "Corporate lawyers & law firms", "value": 32500}, {"rate": 0.08333333333333334, "donations": 12, "name": "Trial lawyers & law firms", "value": 9349}, {"rate": 0.011111111111111112, "donations": 90, "name": "Democratic leadership PAC", "value": 279792}, {"rate": 0.33333333333333337, "donations": 3, "name": "Democratic officials, candidates & former members", "value": 7300}, {"rate": 0.3333333333333333, "donations": 3, "name": "Non-Federal candidate committees", "value": 6900}, {"rate": 1.0, "donations": 1, "name": "Republican officials, candidates & former members", "value": 4000}, {"rate": 1.0, "donations": 1, "name": "Livestock", "value": 1000}, {"rate": 0.25, "donations": 4, "name": "Lobbyists & Public Relations", "value": 9000}, {"rate": 1.0, "donations": 1, "name": "Hotels & motels", "value": 4600}, {"rate": 1.0, "donations": 1, "name": "Correctional facilities constr & mgmt/for-profit", "value": 5000}, {"rate": 1.0, "donations": 1, "name": "Defense-related services", "value": 2000}, {"rate": 1.0, "donations": 1, "name": "Water Utilities", "value": 1000}, {"rate": 0.09090909090909091, "donations": 11, "name": "Labor, anti-union", "value": 33278}, {"rate": 0.25, "donations": 4, "name": "Other single-issue or ideological groups", "value": 3500}, {"rate": 1.0, "donations": 1, "name": "Third-party committees", "value": 51}, {"rate": 1.0, "donations": 1, "name": "Recycling of metal, paper, plastics, etc.", "value": 5000}, {"rate": 0.3333333333333333, "donations": 3, "name": "Services", "value": 2300}, {"rate": 0.5, "donations": 2, "name": "Taxicabs", "value": 4600}, {"rate": 1.0, "donations": 1, "name": "Commercial service unions", "value": 8002}, {"rate": 0.33333333333333337, "donations": 3, "name": "Entertainment unions", "value": 5000}, {"rate": 0.5, "donations": 2, "name": "Food service & related unions", "value": 10000}, {"rate": 0.05555555555555555, "donations": 18, "name": "Labor Unions", "value": 253706}, {"rate": 0.0, "donations": 4, "name": "Other unions", "value": 0}, {"rate": 1.0, "donations": 1, "name": "Internal Transfer and other non-contributions", "value": 6466214}, {"rate": 0.5, "donations": 2, "name": "Independent oil & gas producers", "value": 3300}, {"rate": 1.0, "donations": 1, "name": "Welfare & Social Work", "value": 1000}, {"rate": 0.19999999999999998, "donations": 5, "name": "Democratic Party Committees", "value": 15513}, {"rate": 0.0625, "donations": 16, "name": "Republican Party Committees", "value": 27271}, {"rate": 1.0, "donations": 1, "name": "Third-Party Party Committees", "value": 51}, {"rate": 0.09090909090909091, "donations": 11, "name": "Medical Devices & Supplies", "value": 16000}, {"rate": 0.25, "donations": 4, "name": "Pharmaceutical manufacturing", "value": 9300}, {"rate": 1.0, "donations": 1, "name": "Pharmaceutical wholesale", "value": 2500}, {"rate": 0.25, "donations": 4, "name": "Pro-Israel", "value": 20000}, {"rate": 0.33333333333333337, "donations": 3, "name": "Federal employees unions", "value": 5000}, {"rate": 1.0, "donations": 1, "name": "Police & firefighters unions & associations", "value": 5000}, {"rate": 0.004608294930875576, "donations": 217, "name": "State & local govt employee unions", "value": 11675004}, {"rate": 0.02, "donations": 50, "name": "Teachers unions", "value": 3857887}, {"rate": 0.008, "donations": 125, "name": "US Postal Service unions & associations", "value": 167306}, {"rate": 0.09090909090909091, "donations": 11, "name": "Real Estate developers & subdividers", "value": 21500}, {"rate": 0.0011600928074245941, "donations": 862, "name": "Republican/Conservative", "value": 1452923}, {"rate": 1.0, "donations": 1, "name": "Department, variety & convenience stores", "value": 5000}, {"rate": 1.0, "donations": 1, "name": "Miscellaneous retail stores", "value": 3}, {"rate": 0.2, "donations": 5, "name": "Cruise ships & lines", "value": 25000}, {"rate": 0.3333333333333333, "donations": 3, "name": "Commodity brokers/dealers", "value": 15000}, {"rate": 0.2, "donations": 5, "name": "Private Equity & Investment Firms", "value": 15000}, {"rate": 0.3333333333333333, "donations": 3, "name": "Security brokers & investment companies", "value": 15000}, {"rate": 1.0, "donations": 1, "name": "Stock exchanges", "value": 2900}, {"rate": 1.0, "donations": 1, "name": "Commercial TV & radio stations", "value": 5000}, {"rate": 0.33333333333333337, "donations": 3, "name": "Cable distributors & service providers", "value": 9388}, {"rate": 1.0, "donations": 1, "name": "Satellite communications", "value": 1000}, {"rate": 0.5, "donations": 2, "name": "Telecommunications", "value": 7000}, {"rate": 0.25, "donations": 4, "name": "Telephone utilities", "value": 11600}, {"rate": 0.33333333333333337, "donations": 3, "name": "Air transport unions", "value": 5750}, {"rate": 0.2, "donations": 5, "name": "Merchant marine & longshoremen unions", "value": 16900}, {"rate": 1.0, "donations": 1, "name": "Other transportation unions", "value": 5000}, {"rate": 0.14285714285714285, "donations": 7, "name": "Railroad unions", "value": 20999}, {"rate": 0.025, "donations": 40, "name": "Transportation unions", "value": 88150}, {"rate": 0.16666666666666666, "donations": 6, "name": "Unknown", "value": 14200}, {"rate": 0.004484304932735426, "donations": 223, "name": "Women's issues", "value": 1879778}]}]}